[
    {
        "text": "Genius is one percent inspiration and ninety-nine percent perspiration.",
        "author": "Thomas Edison"
    },
    {
        "text": "You can observe a lot just by watching.",
        "author": "Yogi Berra"
    },
    {
        "text": "A house divided against itself cannot stand.",
        "author": "Abraham Lincoln"
    },
    {
        "text": "Difficulties increase the nearer we get to the goal.",
        "author": "Johann Wolfgang von Goethe"
    },
    {
        "text": "Fate is in your hands and no one elses",
        "author": "Byron Pulsifer"
    },
    {
        "text": "Be the chief but never the lord.",
        "author": "Lao Tzu"
    },
    {
        "text": "Nothing happens unless first we dream.",
        "author": "Carl Sandburg"
    },
    {
        "text": "Well begun is half done.",
        "author": "Aristotle"
    },
    {
        "text": "Life is a learning experience, only if you learn.",
        "author": "Yogi Berra"
    },
    {
        "text": "Self-complacency is fatal to progress.",
        "author": "Margaret Sangster"
    },
    {
        "text": "Peace comes from within. Do not seek it without.",
        "author": "Buddha"
    },
    {
        "text": "What you give is what you get.",
        "author": "Byron Pulsifer"
    },
    {
        "text": "We can only learn to love by loving.",
        "author": "Iris Murdoch"
    },
    {
        "text": "Life is change. Growth is optional. Choose wisely.",
        "author": "Karen Clark"
    },
    {
        "text": "You'll see it when you believe it.",
        "author": "Wayne Dyer"
    },
    {
        "text": "Today is the tomorrow we worried about yesterday.",
        "author": "type.fit"
    },
    {
        "text": "Believe you can and you're halfway there.",
        "author": "Theodore Roosevelt"
    },
    {
        "text": "The only way to do great work is to love what you do.",
        "author": "Steve Jobs"
    },
    {
        "text": "Success is not final, failure is not fatal: It is the courage to continue that counts.",
        "author": "Winston Churchill"
    },
    {
        "text": "Your limitation—it's only your imagination.",
        "author": "Unknown"
    },
    {
        "text": "Push yourself, because no one else is going to do it for you.",
        "author": "Unknown"
    },
    {
        "text": "Great things never come from comfort zones.",
        "author": "Unknown"
    },
    {
        "text": "Dream it. Wish it. Do it.",
        "author": "Unknown"
    },
    {
        "text": "Success doesn't just find you. You have to go out and get it.",
        "author": "Unknown"
    },
    {
        "text": "The harder you work for something, the greater you'll feel when you achieve it.",
        "author": "Unknown"
    },
    {
        "text": "Dream bigger. Do bigger.",
        "author": "Unknown"
    },
    {
        "text": "Don't stop when you're tired. Stop when you're done.",
        "author": "Unknown"
    },
    {
        "text": "Wake up with determination. Go to bed with satisfaction.",
        "author": "Unknown"
    },
    {
        "text": "Do something today that your future self will thank you for.",
        "author": "Unknown"
    },
    {
        "text": "Little things make big days.",
        "author": "Unknown"
    },
    {
        "text": "It's going to be hard, but hard does not mean impossible.",
        "author": "Unknown"
    },
    {
        "text": "Don't wait for opportunity. Create it.",
        "author": "Unknown"
    },
    {
        "text": "Success is not the key to happiness. Happiness is the key to success. If you love what you are doing, you will be successful.",
        "author": "Albert Schweitzer"
    },
    {
        "text": "Don't be pushed around by the fears in your mind. Be led by the dreams in your heart.",
        "author": "Roy T. Bennett"
    },
    {
        "text": "The only person you should try to be better than is the person you were yesterday.",
        "author": "Unknown"
    },
    {
        "text": "The future belongs to those who believe in the beauty of their dreams.",
        "author": "Eleanor Roosevelt"
    }
]